Workbook

Sheet Anleitung
A1: Balancing «Redesign the Last Mile»
A2: Regelversion 2.2.0 · erstellt am 29.10.2026 · Simulation mit 60 Ereignisfolgen pro Strategie
A4: So arbeitet ihr mit dieser Mappe
A5: 1. Blatt «Parameter»: nur die blauen Zahlen in der Spalte «Wert» (gelb hinterlegt) ändern. Jede Zahl hat eine Beschreibung und Einheit.
A6: 2. Blatt «Startnetz»: rechnet mit Formeln, was das unveränderte Diesel-Netz in einer normalen Runde kostet. Es reagiert sofort auf eure Parameter.
A7: 3. Blätter «Teststrategien», «Kalibrierung» und «Sensitivität»: Ergebnisse der automatischen Simulation mit dem echten Rechenkern. Sie ändern sich erst, wenn die Simulation neu läuft.
A8: 4. Geänderte Mappe an Claude geben (oder: python3 tools/excel_to_params.py docs/Balancing.xlsx). Dann wird config/params.json aktualisiert, die Simulation neu gerechnet und das Spiel neu veröffentlicht.
A9: 5. Bei jeder Änderung die Regelversion erhöhen (Parameter «version»), damit die Statistiken nur Spiele mit gleichen Regeln vergleichen.
A11: Farbcode
A12: Blaue Schrift auf Gelb = Eingabe · schwarze Schrift = Formel · grüne Schrift = Bezug auf ein anderes Blatt · graue Werte = Ergebnis der Simulation (kein Formelbezug)
A14: Herkunft der Zahlen
A15: Alle Werte sind bewusst vereinfachte Spielannahmen, kalibriert per Simulation (Kriterien im Blatt «Kalibrierung»). Sie sind keine Kennzahlen realer Unternehmen. Die WEF-Berichte (2020, 2024) und weitere Literatur sind für die finale Kalibrierung noch auszuwerten.

Sheet Parameter
A1: Schlüssel | B1: Bereich | C1: Beschreibung | D1: Wert | E1: Einheit | F1: Quelle / Annahme | H1: Startnetz: 4 Diesel-Vans in S1, je 2 in A2 und A8, je 1 im Zentrum jeder Landregion (in params.json unter startNetwork)
A2: version | B2: Allgemein | C2: Regelversion; bei Änderungen erhöhen (z. B. 2.2.1), damit Statistiken nur gleiche Regeln vergleichen | D2: 2.2.0 | E2: Text | F2: Spielannahme, kalibriert per Simulation
A3: rounds | B3: Allgemein | C3: Standard-Rundenzahl pro Spiel (wählbar 4–6) | D3: 4 | E3: Runden | F3: Spielannahme, kalibriert per Simulation
A4: actionsPerRound | B4: Allgemein | C4: Aktionen pro Team und Runde | D4: 2 | E4: Anzahl | F4: Spielannahme, kalibriert per Simulation
A5: maxTeams | B5: Allgemein | C5: Maximale Anzahl Teams | D5: 5 | E5: Anzahl | F5: Spielannahme, kalibriert per Simulation
A6: upstreamCostPerParcel | B6: Wirtschaftlichkeit | C6: Vorlaufkosten pro Paket (Abholung, Sortierung, Hauptlauf); nur für den Lieferketten-Anteil | D6: 5.5 | E6: CHF/Paket | F6: Spielannahme, kalibriert per Simulation
A7: tariffPerParcel | B7: Wirtschaftlichkeit | C7: Last-Mile-Tarif: Anteil des Paketpreises nach Abzug der Vorlaufkosten; Mindeststandard Kosten ≤ Tarif | D7: 5.6 | E7: CHF/Paket | F7: Spielannahme, kalibriert per Simulation
A8: standards.onTimeNational | B8: Mindeststandards | C8: Pünktlichkeit landesweit, mindestens | D8: 0.9 | E8: Anteil | F8: Spielannahme, kalibriert per Simulation
A9: standards.onTimeZone | B9: Mindeststandards | C9: Pünktlichkeit in jeder Zone, mindestens | D9: 0.8 | E9: Anteil | F9: Spielannahme, kalibriert per Simulation
A10: zones.stadt.demand | B10: Zone Stadt | C10: Pakete pro Team, Feld und Runde | D10: 70 | E10: Pakete | F10: Spielannahme, kalibriert per Simulation
A11: zones.stadt.distance | B11: Zone Stadt | C11: Distanzfaktor auf variable Kosten und CO₂ von Fahrzeugen | D11: 1 | E11: Faktor | F11: Spielannahme, kalibriert per Simulation
A12: zones.stadt.failRate | B12: Zone Stadt | C12: Fehlzustellungsrate bei Haustürzustellung (Standardpolitik) | D12: 0.12 | E12: Anteil | F12: Spielannahme, kalibriert per Simulation
A13: zones.stadt.timeWindowCapacityLoss | B13: Zone Stadt | C13: Kapazitätsverlust eigener Fahrzeuge bei Zeitfenstern | D13: 0.15 | E13: Anteil | F13: Spielannahme, kalibriert per Simulation
A14: zones.agglo.demand | B14: Zone Agglo | C14: Pakete pro Team, Feld und Runde | D14: 30 | E14: Pakete | F14: Spielannahme, kalibriert per Simulation
... A98: events.extraAnnouncements | B98: Ereignisse | C98: Zusätzliche Ankündigungen (CO₂-Abgabe oder Boxen beliebter) | D98: 1 | E98: Anzahl | F98: Spielannahme, kalibriert per Simulation

Sheet Startnetz
A1: Kostenstruktur des Startnetzes in einer normalen Runde (ohne Ereignisse)
A2: Vereinfachte Rechnung mit Formeln: Fixkosten nach Standortzone, variable Kosten nach Zustellzone. Vergleichswert aus dem Rechenkern in Spalte H.
A4: Zone | B4: Felder | C4: Pakete | D4: Diesel-Vans (Standort) | E4: Fixkosten | F4: Variable Kosten inkl. Zweitzustellung | G4: Kosten pro Paket | H4: Rechenkern Runde 1 | I4: Kapazitätsbedarf (Einheiten)
A5: Stadt | B5: 7 | C5: =B5*Parameter!$D$10 -> 490 | D5: 4 | E5: =D5*(Parameter!$D$24+Parameter!$D$23) -> 1640 | F5: =C5*Parameter!$D$26*Parameter!$D$11*(1+Parameter!$D$12) -> 137.2 | G5: =(E5+F5)/C5 -> 3.6269388 | H5: 3.63 | I5: =C5*Parameter!$D$30*(1+Parameter!$D$12) -> 548.8
A6: Agglo | B6: 11 | C6: =B6*Parameter!$D$14 -> 330 | D6: 4 | E6: =D6*(Parameter!$D$24+Parameter!$D$23) -> 1640 | F6: =C6*Parameter!$D$26*Parameter!$D$15*(1+Parameter!$D$16) -> 122.43 | G6: =(E6+F6)/C6 -> 5.340697 | H6: 5.34 | I6: =C6*Parameter!$D$31*(1+Parameter!$D$16) -> 437.25
A7: Land | B7: 15 | C7: =B7*Parameter!$D$18 -> 120 | D7: 3 | E7: =D7*(Parameter!$D$24+Parameter!$D$23) -> 1230 | F7: =C7*Parameter!$D$26*Parameter!$D$19*(1+Parameter!$D$20) -> 93.6 | G7: =(E7+F7)/C7 -> 11.03 | H7: 11.03 | I7: =C7*Parameter!$D$32*(1+Parameter!$D$20) -> 324.48
A8: Total | B8: =SUM(B5:B7) -> 33 | C8: =SUM(C5:C7) -> 940 | D8: =SUM(D5:D7) -> 11 | E8: =SUM(E5:E7) -> 4510 | F8: =SUM(F5:F7) -> 353.23 | G8: =(E8+F8)/C8 -> 5.1736489 | I8: =SUM(I5:I7) -> 1310.53
A10: Kapazität der Diesel-Vans im Startnetz (Einheiten) | G10: =D8*Parameter!$D$28 -> 1430
A11: Auslastung des Startnetzes | G11: =I8/G10 -> 0.91645455
A12: Anteil letzte Meile an den gesamten Paketkosten | G12: =G8/(G8+Parameter!$D$6) -> 0.4847123
A13: Last-Mile-Tarif | G13: =Parameter!$D$7 -> 5.6
A14: Abstand Startnetz zum Tarif (negativ = teurer als Tarif) | G14: =G13-G8 -> 0.42635106
A16: Hinweis: Die Stadt-Vans in S1 bedienen auch die Agglo; die Zuordnung der Fixkosten folgt dem Standort (Spalte D). Kleine Abweichungen zu Spalte H entstehen, weil der Rechenkern die Pakete feldgenau zuteilt.

Sheet Teststrategien
A1: Ergebnisse der Simulation: 60 Ereignisfolgen pro Strategie, je ein Team allein, 4 Runden
A3: Schlüssel | B3: Strategie | C3: Kosten pro Paket (CHF) | D3: Pünktlichkeit | E3: CO₂ pro Paket (g) | F3: Fehlzustellungen | G3: Alle Standards erfüllt | H3: Standard landesweit | I3: Standard Kosten | J3: Standard alle Zonen | K3: Pünktl. Stadt | L3: Pünktl. Agglo | M3: Pünktl. Land | N3: Anteil letzte Meile | O3: Bewertung
A4: nichts | B4: Nichts ändern (nur Diesel) | C4: 7.4497498 | D4: 0.66597935 | E4: 424.93243 | F4: 0.070036676 | G4: 0 | H4: 0 | I4: 0 | J4: 0 | K4: 0.43062775 | L4: 0.91796922 | M4: 0.93706024 | N4: 0.57463415 | O4: =IF(G4>=0.5,"trägt",IF(G4>0,"selten","scheitert")) -> scheitert
A5: hubsStadt | B5: Früh grün: Hubs in der Stadt, Post auf dem Land | C5: 5.8157909 | D5: 0.89740354 | E5: 281.57728 | F5: 0.088065306 | G5: 0.1 | H5: 0.43333333 | I5: 0.13333333 | J5: 1 | K5: 0.87326502 | L5: 0.92603555 | M5: 0.9175368 | N5: 0.5138165 | O5: =IF(G5>=0.5,"trägt",IF(G5>0,"selten","scheitert")) -> selten
A6: hubsGeschickt | B6: Hubs in der Stadt mit Zeitfenstern, Post auf dem Land | C6: 5.9087271 | D6: 0.90574492 | E6: 281.68908 | F6: 0.073950814 | G6: 0.066666667 | H6: 0.66666667 | I6: 0.066666667 | J6: 1 | K6: 0.88982574 | L6: 0.91936644 | M6: 0.93327473 | N6: 0.51770968 | O6: =IF(G6>=0.5,"trägt",IF(G6>0,"selten","scheitert")) -> selten
A7: boxenHubs | B7: Boxen und Hubs in der Stadt, Post auf dem Land | C7: 5.8302895 | D7: 0.91114399 | E7: 281.46809 | F7: 0.065107727 | G7: 0.13333333 | H7: 0.73333333 | I7: 0.13333333 | J7: 1 | K7: 0.89684643 | L7: 0.92619059 | M7: 0.92821928 | N7: 0.5143886 | O7: =IF(G7>=0.5,"trägt",IF(G7>0,"selten","scheitert")) -> selten
A8: mixZonen | B8: Mix nach Zonen: Boxen Stadt, Post Land, E-Vans | C8: 5.4404625 | D8: 0.91951733 | E8: 263.39794 | F8: 0.057865866 | G8: 0.71666667 | H8: 0.81666667 | I8: 0.76666667 | J8: 1 | K8: 0.92697242 | L8: 0.90670848 | M8: 0.92433964 | N8: 0.49694927 | O8: =IF(G8>=0.5,"trägt",IF(G8>0,"selten","scheitert")) -> trägt
A9: stadtMax | B9: Stadt maximieren, Land vernachlässigen | C9: 5.3262842 | D9: 0.85645589 | E9: 311.90367 | F9: 0.055411973 | G9: 0 | H9: 0.033333333 | I9: 0.8 | J9: 0 | K9: 0.90771148 | L9: 0.88689277 | M9: 0.56324952 | N9: 0.49155401 | O9: =IF(G9>=0.5,"trägt",IF(G9>0,"selten","scheitert")) -> scheitert
A10: boxPost | B10: Boxen überall, Post auf dem Land | C10: 5.4767059 | D10: 0.91714007 | E10: 239.18934 | F10: 0.061748795 | G10: 0.71666667 | H10: 0.9 | I10: 0.71666667 | J10: 1 | K10: 0.90640562 | L10: 0.93507024 | M10: 0.91189102 | N10: 0.49881453 | O10: =IF(G10>=0.5,"trägt",IF(G10>0,"selten","scheitert")) -> trägt
A11: zeitfenster | B11: Zeitfenster in allen Zonen | C11: 6.7637277 | D11: 0.78211379 | E11: 350.88863 | F11: 0.04636535 | G11: 0 | H11: 0 | I11: 0 | J11: 0.016666667 | K11: 0.71525587 | L11: 0.83494699 | M11: 0.91028965 | N11: 0.5512373 | O11: =IF(G11>=0.5,"trägt",IF(G11>0,"selten","scheitert")) -> scheitert
A12: vieleVans | B12: Viele zusätzliche Vans | C12: 18.968129 | D12: 0.91125028 | E12: 310.99048 | F12: 0.088749723 | G12: 0 | H12: 1 | I12: 0 | J12: 1 | K12: 0.88 | L12: 0.94 | M12: 0.96 | N12: 0.77496491 | O12: =IF(G12>=0.5,"trägt",IF(G12>0,"selten","scheitert")) -> scheitert
A13: postUndFlotte | B13: Post-Vertrag, aber eigene Land-Vans behalten | C13: 6.425953 | D13: 0.81515501 | E13: 334.44321 | F13: 0.081641865 | G13: 0 | H13: 0 | I13: 0 | J13: 0.016666667 | K13: 0.74096449 | L13: 0.87388477 | M13: 0.95737149 | N13: 0.53856534 | O13: =IF(G13>=0.5,"trägt",IF(G13>0,"selten","scheitert")) -> scheitert
A14: spaetBauen | B14: Hub und Box erst spät | C14: 5.973244 | D14: 0.8529215 | E14: 314.94338 | F14: 0.079005639 | G14: 0.016666667 | H14: 0.016666667 | I14: 0.033333333 | J14: 0.51666667 | K14: 0.78917453 | L14: 0.91730294 | M14: 0.93706024 | N14: 0.52044844 | O14: =IF(G14>=0.5,"trägt",IF(G14>0,"selten","scheitert")) -> selten
A15: ungenutzterVan | B15: Ungenutzter Van an der Zonengrenze | C15: 6.585866 | D15: 0.84003425 | E15: 335.18216 | F15: 0.083355522 | G15: 0 | H15: 0 | I15: 0 | J15: 0.28333333 | K15: 0.78228488 | L15: 0.89089167 | M15: 0.93706024 | N15: 0.54467823 | O15: =IF(G15>=0.5,"trägt",IF(G15>0,"selten","scheitert")) -> scheitert
A17: Viererpartien (je Seed eine Partie)
A18: mixZonen vs. hubsStadt vs. boxPost vs. nichts | B18: Siege: mixZonen 28, hubsStadt 0, boxPost 19, nichts 0 · ohne Sieger: 13
A19: mixZonen vs. zeitfenster vs. stadtMax vs. vieleVans | B19: Siege: mixZonen 13, zeitfenster 0, stadtMax 0, vieleVans 0 · ohne Sieger: 47
A20: hubsGeschickt vs. boxPost vs. mixZonen vs. boxenHubs | B20: Siege: hubsGeschickt 1, boxPost 18, mixZonen 25, boxenHubs 0 · ohne Sieger: 16
A22: Arbeitsmarkt: Kosten pro Paket eines Teams «Mix nach Zonen» mit und ohne ein Team, das massiv Vans einstellt
A23: ohne | C23: 5.1570357
A24: mit | C24: 5.56221
A25: Mehrkosten für das andere Team | C25: =C24/C23-1 -> 0.078567282

Sheet Kalibrierung
A1: Kalibrierungskriterien aus dem Prüfdossier (Version 2.1) und ihre Prüfung
A3: Nr. | B3: Kriterium | C3: Messung | D3: Wert | E3: Ergebnis
A4: 1 | B4: Startnetz verfehlt unter Belastung mindestens einen Standard | C4: Anteil Ereignisfolgen, in denen «Nichts ändern» alle Standards erfüllt | D4: =Teststrategien!G4 -> 0 | E4: =IF(D4=0,"erfüllt","verfehlt") -> erfüllt
A5: 2 | B5: Mindestens zwei unterschiedliche Strategien erfüllen alle Standards | C5: Anzahl Strategien mit Erfolgsquote ≥ 50 % | D5: =COUNTIF(Teststrategien!G4:G25,">=0.5") -> 2 | E5: =IF(D5>=2,"erfüllt","verfehlt") -> erfüllt
A6: 3 | B6: Kein Element ist in allen Zonen das beste | C6: Hub nur Stadt, Box auf dem Land teuer, Post nur Land (Regel) | D6: Regel im Modell | E6: erfüllt
A7: 4 | B7: Tarif wirtschaftlich begründet | C7: Paketpreis = Tarif + Vorlaufkosten | D7: =Parameter!$D$7+Parameter!$D$6 -> 11.1 | E7: ="Paketpreis CHF "&TEXT(D7,"0.00") -> Paketpreis CHF 11.10
A8: 5 | B8: Anteil letzte Meile im Startnetz 40–50 % | C8: aus Blatt Startnetz | D8: =Startnetz!G12 -> 0.4847123 | E8: =IF(AND(D8>=0.4,D8<=0.5),"erfüllt","verfehlt") -> erfüllt
A9: 6 | B9: Rangfolge robust bei ±20 % je Parameter | C9: Variationen mit unveränderten Top 2 (von 16) | D9: =COUNTIF(Sensitivität!F4:F19,"stabil") -> 15 | E9: =IF(D9>=14,"erfüllt","prüfen") -> erfüllt
A11: Befund Sensitivität: Steigen die Löhne um 20 %, erfüllt kaum noch eine Strategie den Kostenstandard. Wer Löhne erhöht, sollte den Tarif mitprüfen.

Sheet Sensitivität
A1: Sensitivität: je ein Parameter um −20 % bzw. +20 % verändert, 30 Ereignisfolgen pro Strategie
A3: Parameter | B3: Faktor | C3: Beste Strategie | D3: Zweitbeste | E3: Startnetz scheitert weiter | F3: Top 2 unverändert
A4: Post: Kosten pro Paket | B4: 0.8 | C4: Mix nach Zonen: Boxen Stadt, Post Land, E-Vans | D4: Boxen überall, Post auf dem Land | E4: ja | F4: stabil
A5: Post: Kosten pro Paket | B5: 1.2 | C5: Mix nach Zonen: Boxen Stadt, Post Land, E-Vans | D5: Boxen überall, Post auf dem Land | E5: ja | F5: stabil
A6: Box: Miete pro Feld | B6: 0.8 | C6: Boxen überall, Post auf dem Land | D6: Mix nach Zonen: Boxen Stadt, Post Land, E-Vans | E6: ja | F6: stabil
A7: Box: Miete pro Feld | B7: 1.2 | C7: Mix nach Zonen: Boxen Stadt, Post Land, E-Vans | D7: Boxen überall, Post auf dem Land | E7: ja | F7: stabil
A8: Hub: Kapazität | B8: 0.8 | C8: Mix nach Zonen: Boxen Stadt, Post Land, E-Vans | D8: Boxen überall, Post auf dem Land | E8: ja | F8: stabil
A9: Hub: Kapazität | B9: 1.2 | C9: Mix nach Zonen: Boxen Stadt, Post Land, E-Vans | D9: Boxen überall, Post auf dem Land | E9: ja | F9: stabil
A10: E-Van: Leasing | B10: 0.8 | C10: Mix nach Zonen: Boxen Stadt, Post Land, E-Vans | D10: Boxen überall, Post auf dem Land | E10: ja | F10: stabil
A11: E-Van: Leasing | B11: 1.2 | C11: Mix nach Zonen: Boxen Stadt, Post Land, E-Vans | D11: Boxen überall, Post auf dem Land | E11: ja | F11: stabil
A12: Fahrerlohn (alle Vans) | B12: 0.8 | C12: Boxen überall, Post auf dem Land | D12: Mix nach Zonen: Boxen Stadt, Post Land, E-Vans | E12: ja | F12: stabil
A13: Fahrerlohn (alle Vans) | B13: 1.2 | C13: Mix nach Zonen: Boxen Stadt, Post Land, E-Vans | D13: Stadt maximieren, Land vernachlässigen | E13: ja | F13: Wechsel
A14: Notfall: Kosten pro Paket | B14: 0.8 | C14: Mix nach Zonen: Boxen Stadt, Post Land, E-Vans | D14: Boxen überall, Post auf dem Land | E14: ja | F14: stabil
A15: Notfall: Kosten pro Paket | B15: 1.2 | C15: Mix nach Zonen: Boxen Stadt, Post Land, E-Vans | D15: Boxen überall, Post auf dem Land | E15: ja | F15: stabil
... A19: Fehlzustellung Stadt | B19: 1.2 | C19: Mix nach Zonen: Boxen Stadt, Post Land, E-Vans | D19: Boxen überall, Post auf dem Land | E19: ja | F19: stabil
A21: Basis (unverändert): Mix nach Zonen: Boxen Stadt, Post Land, E-Vans > Boxen überall, Post auf dem Land > Boxen und Hubs in der Stadt, Post auf dem Land
